MANIFEST.in
README.rst
setup.py
examples/__init__.py
examples/run_label_propagation.py
semisupervised/GraphBasedSSL.py
semisupervised/PseudoLabelSSL.py
semisupervised/SklearnLabelPropagation.py
semisupervised/StackedAutoEncoderSSL.py
semisupervised/TSVM.py
semisupervised/__init__.py
semisupervised/qns3vm.py
semisupervised.egg-info/PKG-INFO
semisupervised.egg-info/SOURCES.txt
semisupervised.egg-info/dependency_links.txt
semisupervised.egg-info/requires.txt
semisupervised.egg-info/top_level.txt